Lab3
Lab3/constants
Lab3/funcs
Lab3/package
