Metadata-Version: 2.1
Name: serializer-from-hell
Version: 1.1
Summary: json and xml sers
Home-page: UNKNOWN
Author-email: sea25042003@gmail.com
License: UNKNOWN
Platform: UNKNOWN
